{
  "id": "feedback_section",
  "type": "SharedSlice",
  "name": "FeedbackSection",
  "description": "FeedbackSection",
  "variations": [
    {
      "id": "default",
      "name": "Default",
      "docURL": "...",
      "version": "initial",
      "description": "Default",
      "imageUrl": "",
      "primary": {
        "title": {
          "type": "StructuredText",
          "config": {
            "label": "Title",
            "placeholder": "",
            "allowTargetBlank": true,
            "multi": "paragraph,preformatted,heading1,heading2,heading3,heading4,heading5,heading6,strong,em,hyperlink,image,embed,list-item,o-list-item,rtl"
          }
        }
      },
      "items": {
        "feedback_title": {
          "type": "StructuredText",
          "config": {
            "label": "Feedback Title",
            "placeholder": "",
            "allowTargetBlank": true,
            "multi": "paragraph,preformatted,heading1,heading2,heading3,heading4,heading5,heading6,strong,em,hyperlink,image,embed,list-item,o-list-item,rtl"
          }
        },
        "feedback_description": {
          "type": "StructuredText",
          "config": {
            "label": "Feedback Description",
            "placeholder": "",
            "allowTargetBlank": true,
            "multi": "paragraph,preformatted,heading1,heading2,heading3,heading4,heading5,heading6,strong,em,hyperlink,image,embed,list-item,o-list-item,rtl"
          }
        },
        "feedback_name": {
          "type": "StructuredText",
          "config": {
            "label": "Feedback Name",
            "placeholder": "",
            "allowTargetBlank": true,
            "multi": "paragraph,preformatted,heading1,heading2,heading3,heading4,heading5,heading6,strong,em,hyperlink,image,embed,list-item,o-list-item,rtl"
          }
        },
        "feedback_image": {
          "type": "Image",
          "config": {
            "label": "Feedback Image",
            "constraint": {},
            "thumbnails": []
          }
        }
      }
    }
  ]
}